phonexia_speaker_diarization_client.py
phonexia_speaker_diarization_client-2.0.1.dist-info/METADATA
phonexia_speaker_diarization_client-2.0.1.dist-info/WHEEL
phonexia_speaker_diarization_client-2.0.1.dist-info/entry_points.txt
phonexia_speaker_diarization_client-2.0.1.dist-info/top_level.txt
phonexia_speaker_diarization_client-2.0.1.dist-info/RECORD
