Metadata-Version: 2.4
Name: phonexia-speaker-diarization-client
Version: 2.0.1
Summary: Client script for communication with diarization microservice
Author-email: Phonexia <info@phonexia.com>
Keywords: grpc,voice,voice-biometry,speech,language,diarization
Requires-Python: >=3.9
Requires-Dist: more-itertools>=10.6.0
Requires-Dist: phonexia-grpc>=2.27.1
Requires-Dist: numpy>=2.0.0; python_version >= "3.12"
Requires-Dist: numpy<2.0.0; python_version < "3.12"
Requires-Dist: typer>=0.16.0
Requires-Dist: soundfile>=0.13.0
